jsonshiatsu/__init__.py
jsonshiatsu/core/__init__.py
jsonshiatsu/core/engine.py
jsonshiatsu/core/tokenizer.py
jsonshiatsu/core/transformer.py
jsonshiatsu/recovery/__init__.py
jsonshiatsu/recovery/strategies.py
jsonshiatsu/security/__init__.py
jsonshiatsu/security/exceptions.py
jsonshiatsu/security/limits.py
jsonshiatsu/streaming/__init__.py
jsonshiatsu/streaming/processor.py
jsonshiatsu/utils/__init__.py
jsonshiatsu/utils/cli.py
jsonshiatsu/utils/config.py
jsonshiatsu-0.2.1.dist-info/LICENSE
jsonshiatsu-0.2.1.dist-info/METADATA
jsonshiatsu-0.2.1.dist-info/WHEEL
jsonshiatsu-0.2.1.dist-info/RECORD
