Metadata-Version: 2.3
Name: jsonshiatsu
Version: 0.2.1
Summary: A therapeutic JSON parser that gently massages malformed JSON into shape
License: MIT
Keywords: json,parser,therapeutic,massage,malformed,resilient,shiatsu
Author: Jost Brandstetter
Author-email: brandstetterjost@gmail.com
Requires-Python: >=3.9,<3.14
Classifier: Development Status :: 3 - Alpha
Classifier: Intended Audience :: Developers
Classifier: License :: OSI Approved :: MIT License
Classifier: Operating System :: OS Independent
Classifier: Programming Language :: Python :: 3
Classifier: Programming Language :: Python :: 3.9
Classifier: Programming Language :: Python :: 3.10
Classifier: Programming Language :: Python :: 3.11
Classifier: Programming Language :: Python :: 3.12
Classifier: Programming Language :: Python :: 3.13
Classifier: Topic :: Software Development :: Libraries :: Python Modules
Classifier: Topic :: Text Processing :: Markup
Classifier: Topic :: Utilities
Requires-Dist: pre-commit (>=4.3.0,<5.0.0)
Project-URL: Documentation, https://github.com/JostBrand/jsonshiatsu
Project-URL: Homepage, https://github.com/JostBrand/jsonshiatsu
Project-URL: Repository, https://github.com/JostBrand/jsonshiatsu
